{
  "kind": "collectionType",
  "collectionName": "sucursales",
  "info": {
    "singularName": "sucursal",
    "pluralName": "sucursales",
    "displayName": "Sucursales",
    "description": ""
  },
  "options": {
    "draftAndPublish": false
  },
  "pluginOptions": {},
  "attributes": {
    "nombre": {
      "type": "string",
      "required": true
    },
    "calle": {
      "type": "string"
    },
    "colonia": {
      "type": "string"
    },
    "numero_exterior": {
      "type": "string"
    },
    "numero_interior": {
      "type": "string"
    },
    "codigo_postal": {
      "type": "integer"
    },
    "municipio": {
      "type": "string"
    },
    "estado": {
      "type": "string"
    },
    "rfc_emisor": {
      "type": "string"
    },
    "nombre_fiscal_emisor": {
      "type": "string"
    },
    "regimen_fiscal_emisor": {
      "type": "string"
    },
    "certificado_facturacion": {
      "type": "text"
    },
    "key_facturacion": {
      "type": "text"
    },
    "clave_facturacion": {
      "type": "text"
    },
    "password_sifei": {
      "type": "text"
    },
    "token_sifei_pdf": {
      "type": "text"
    },
    "id_equipo_sifei": {
      "type": "text"
    },
    "password_soap_sifei": {
      "type": "text"
    },
    "user_sifei": {
      "type": "string"
    }
  }
}
